LICENSE-MIT
MANIFEST.in
README.md
pyproject.toml
setup.cfg
setup.py
sdata/__init__.py
sdata/base.py
sdata/blob.py
sdata/data.py
sdata/doe.py
sdata/file.py
sdata/image.py
sdata/metadata.py
sdata/node.py
sdata/parameter.py
sdata/parameters_deprecated.py
sdata/suuid.py
sdata/timestamp.py
sdata/tools.py
sdata/workbook.py
sdata.egg-info/PKG-INFO
sdata.egg-info/SOURCES.txt
sdata.egg-info/dependency_links.txt
sdata.egg-info/requires.txt
sdata.egg-info/top_level.txt
sdata/contrib/__init__.py
sdata/contrib/semver.py
sdata/contrib/sobol_seq.py
sdata/contrib/sqlitedict.py
sdata/contrib/attrdict/__init__.py
sdata/contrib/attrdict/default.py
sdata/contrib/attrdict/dictionary.py
sdata/contrib/attrdict/mapping.py
sdata/contrib/attrdict/merge.py
sdata/contrib/attrdict/mixins.py
sdata/contrib/piexif/__init__.py
sdata/contrib/piexif/_common.py
sdata/contrib/piexif/_dump.py
sdata/contrib/piexif/_exceptions.py
sdata/contrib/piexif/_exif.py
sdata/contrib/piexif/_insert.py
sdata/contrib/piexif/_load.py
sdata/contrib/piexif/_remove.py
sdata/contrib/piexif/_transplant.py
sdata/contrib/piexif/_webp.py
sdata/contrib/piexif/helper.py
sdata/contrib/ranger/__init__.py
sdata/contrib/ranger/collections/__init__.py
sdata/contrib/ranger/collections/rangebucketmap.py
sdata/contrib/ranger/collections/rangemap.py
sdata/contrib/ranger/collections/rangeset.py
sdata/contrib/ranger/range/__init__.py
sdata/contrib/ranger/range/cut.py
sdata/contrib/ranger/range/range.py
sdata/contrib/simple_graph_db/LICENSE
sdata/contrib/simple_graph_db/__init__.py
sdata/contrib/simple_graph_db/database.py
sdata/contrib/simple_graph_db/schema.sql
sdata/contrib/sortedcontainers/LICENSE
sdata/contrib/sortedcontainers/__init__.py
sdata/contrib/sortedcontainers/sorteddict.py
sdata/contrib/sortedcontainers/sortedlist.py
sdata/contrib/sortedcontainers/sortedset.py
sdata/contrib/timeflake/__init__.py
sdata/contrib/timeflake/flake.py
sdata/contrib/timeflake/utils.py
sdata/experiments/__init__.py
sdata/experiments/ks2.py
sdata/experiments/lapshear.py
sdata/experiments/material.py
sdata/iolib/__init__.py
sdata/iolib/db.py
sdata/iolib/hashtree.py
sdata/iolib/hdf.py
